coocop/__init__.py
coocop/coocop.py
coocop-0.2.dist-info/LICENSE
coocop-0.2.dist-info/METADATA
coocop-0.2.dist-info/WHEEL
coocop-0.2.dist-info/top_level.txt
coocop-0.2.dist-info/RECORD
