Metadata-Version: 2.1
Name: coocop
Version: 0.2
Summary: Copyout and CopyPaiting Image Augmentation
Home-page: https://github.com/t-systems-on-site-services-gmbh/coocop
Author: Philip May
Author-email: pm@eniak.de
Maintainer: Philip May
License: UNKNOWN
Keywords: augmentation CNN
Platform: UNKNOWN
Classifier: Intended Audience :: Education
Classifier: Intended Audience :: Science/Research
Classifier: Intended Audience :: Developers
Classifier: Programming Language :: Python :: 3
Classifier: Topic :: Scientific/Engineering
Classifier: Topic :: Software Development
Classifier: License :: OSI Approved :: BSD License
Classifier: Operating System :: OS Independent
Requires-Python: >=3.6
Requires-Dist: numpy
